brickalistest/TD.py
brickalistest/__init__.py
brickalistest-0.4.8.dist-info/LICENSE
brickalistest-0.4.8.dist-info/METADATA
brickalistest-0.4.8.dist-info/WHEEL
brickalistest-0.4.8.dist-info/entry_points.txt
brickalistest-0.4.8.dist-info/RECORD
